{
    "path": "240922_relu_decom_all_case_with_R_relu_d2_w256_cd2_cd256_R2_8192_decom_dim_uv_lr0.0005_knights",
    "depth": 2,
    "width": 256,
    "coord_depth": 2,
    "coord_width": 256,
    "dataset_name": "knights",
    "model_info": "relu",
    "lr": 0.0005,
    "batch_size": 8192,
    "omega": 5,
    "sigma": 5,
    "decom_dim": "uv",
    "R": 2,
    "schdule_type": "linear",
    "lr_gamma": 0.995,
    "lr_linear_C": 1,
    "result": {
        "0": 0,
        "10": 23.403917593900093,
        "20": 23.483437420784405,
        "30": 24.571662340834603,
        "40": 25.0388856936702,
        "50": 24.763438978035037,
        "60": 25.15867498791626,
        "70": 24.86745430649704,
        "80": 25.38824013617706,
        "90": 25.735964903245442,
        "100": 25.97067823392215,
        "110": 26.10611614348071,
        "120": 25.511117853674357,
        "130": 25.974166891659454,
        "140": 26.169974457008,
        "150": 26.261661054272775,
        "160": 26.497408012633038,
        "170": 26.644116184330603,
        "180": 26.34492533726267,
        "190": 26.69510350563597,
        "200": 26.718587073145944,
        "210": 26.710290088120068,
        "220": 26.824004035763,
        "230": 26.876555378182367,
        "240": 26.85770797026092,
        "250": 26.915799323644297,
        "260": 26.841205742561378,
        "270": 26.96651702846454,
        "280": 26.969209257321594,
        "290": 27.01958945123736,
        "300": 27.088001373055768
    },
    "result_time": {
        "10": {
            "forward": 0.6744236051842887,
            "backward": 1.4041243398168888,
            "per_epoch_whole": 22505.70703125,
            "inference_time": 14.352803548177082
        },
        "20": {
            "forward": 0.6685852284469078,
            "backward": 1.394411993403122,
            "per_epoch_whole": 22375.20703125,
            "inference_time": 14.163384755452475
        },
        "30": {
            "forward": 0.7014265671230622,
            "backward": 1.5216145021615153,
            "per_epoch_whole": 24271.748046875,
            "inference_time": 14.339313824971518
        },
        "40": {
            "forward": 0.6711698029460993,
            "backward": 1.3812884774097596,
            "per_epoch_whole": 22189.05078125,
            "inference_time": 14.111911031934952
        },
        "50": {
            "forward": 0.668215425820395,
            "backward": 1.3900689175900227,
            "per_epoch_whole": 22235.74609375,
            "inference_time": 14.33396265241835
        },
        "60": {
            "forward": 0.6642220310873254,
            "backward": 1.3905810241210368,
            "per_epoch_whole": 22301.103515625,
            "inference_time": 14.394879976908365
        },
        "70": {
            "forward": 0.7088467680291606,
            "backward": 1.574882470496696,
            "per_epoch_whole": 24916.1875,
            "inference_time": 14.587150255839031
        },
        "80": {
            "forward": 0.7386552591302109,
            "backward": 1.6320796014811898,
            "per_epoch_whole": 25922.982421875,
            "inference_time": 14.376320097181534
        },
        "90": {
            "forward": 0.722601072469593,
            "backward": 1.6141009622843123,
            "per_epoch_whole": 25645.4453125,
            "inference_time": 14.282588322957356
        },
        "100": {
            "forward": 0.7498864459653704,
            "backward": 1.6794713671000177,
            "per_epoch_whole": 26607.361328125,
            "inference_time": 14.571406364440918
        },
        "110": {
            "forward": 0.6710271241858708,
            "backward": 1.3888869485769495,
            "per_epoch_whole": 22307.029296875,
            "inference_time": 14.45172617170546
        },
        "120": {
            "forward": 0.6765014870756079,
            "backward": 1.39029284741947,
            "per_epoch_whole": 22359.685546875,
            "inference_time": 14.259896808200413
        },
        "130": {
            "forward": 0.6727487023172132,
            "backward": 1.3882172355189797,
            "per_epoch_whole": 22308.4375,
            "inference_time": 14.225166320800781
        },
        "140": {
            "forward": 0.666303484046436,
            "backward": 1.3892254016932388,
            "per_epoch_whole": 22272.658203125,
            "inference_time": 14.30086040496826
        },
        "150": {
            "forward": 0.6647024188983439,
            "backward": 1.3847067202844159,
            "per_epoch_whole": 22168.525390625,
            "inference_time": 14.34961774614122
        },
        "160": {
            "forward": 0.6672059682884229,
            "backward": 1.3881123949705807,
            "per_epoch_whole": 22257.513671875,
            "inference_time": 14.489468574523926
        },
        "170": {
            "forward": 0.6784980386095966,
            "backward": 1.3899829622267788,
            "per_epoch_whole": 22370.0078125,
            "inference_time": 14.325788391960991
        },
        "180": {
            "forward": 0.6742859891902605,
            "backward": 1.3805973148134503,
            "per_epoch_whole": 22180.23046875,
            "inference_time": 14.342051400078665
        },
        "190": {
            "forward": 0.7446506365643828,
            "backward": 1.6752124639762909,
            "per_epoch_whole": 26644.57421875,
            "inference_time": 14.33566231197781
        },
        "200": {
            "forward": 0.7398193430181251,
            "backward": 1.664061907305014,
            "per_epoch_whole": 26418.998046875,
            "inference_time": 14.430225584242079
        },
        "210": {
            "forward": 0.6700890175740354,
            "backward": 1.390688090021213,
            "per_epoch_whole": 22302.802734375,
            "inference_time": 14.58425235748291
        },
        "220": {
            "forward": 0.6764618233039601,
            "backward": 1.3823161002467588,
            "per_epoch_whole": 22250.115234375,
            "inference_time": 14.308433744642471
        },
        "230": {
            "forward": 0.6665568475041063,
            "backward": 1.3856984637548693,
            "per_epoch_whole": 22201.9765625,
            "inference_time": 14.634826660156246
        },
        "240": {
            "forward": 0.6668258238081045,
            "backward": 1.3860644782703162,
            "per_epoch_whole": 22189.77734375,
            "inference_time": 14.566254191928438
        },
        "250": {
            "forward": 0.6762908551145914,
            "backward": 1.3830966335885562,
            "per_epoch_whole": 22239.302734375,
            "inference_time": 14.15257602267795
        },
        "260": {
            "forward": 0.6784254742019311,
            "backward": 1.3873452811814397,
            "per_epoch_whole": 22349.234375,
            "inference_time": 14.189429389105904
        },
        "270": {
            "forward": 0.7209648199276281,
            "backward": 1.649268353312798,
            "per_epoch_whole": 25927.1484375,
            "inference_time": 14.333689053853353
        },
        "280": {
            "forward": 0.7297038514115481,
            "backward": 1.6385921598202595,
            "per_epoch_whole": 25895.345703125,
            "inference_time": 14.580551253424751
        },
        "290": {
            "forward": 0.7240279028288822,
            "backward": 1.6432833181094768,
            "per_epoch_whole": 26021.951171875,
            "inference_time": 14.104451497395834
        },
        "300": {
            "forward": 0.6668434700699822,
            "backward": 1.3885140791535129,
            "per_epoch_whole": 22221.86328125,
            "inference_time": 14.310101403130425
        }
    }
}