{
    "path": "240825_decom_coord_depth_width_relu_d2_w256_cd3_cd768_R1_8192_decom_dim_us_lr0.0005_knights",
    "depth": 2,
    "width": 256,
    "coord_depth": 3,
    "coord_width": 768,
    "dataset_name": "knights",
    "model_info": "relu",
    "lr": 0.0005,
    "batch_size": 8192,
    "omega": 5,
    "sigma": 5,
    "decom_dim": "us",
    "R": 1,
    "result": {
        "0": 0,
        "10": 19.91987728780292,
        "20": 21.814072296309078,
        "30": 22.086806476519282,
        "40": 21.65480246529673,
        "50": 22.360816798466054,
        "60": 23.278548541519623,
        "70": 23.390022782369474,
        "80": 22.739185069897836,
        "90": 23.615791384642446,
        "100": 23.405958984739684,
        "110": 24.01159381835133,
        "120": 24.191230280168433,
        "130": 23.633338738504936,
        "140": 23.073285138555068,
        "150": 24.120046649858253,
        "160": 24.470745939842175,
        "170": 24.344199092398625,
        "180": 24.38381810979376,
        "190": 24.705489824034203,
        "200": 24.357103424846358,
        "210": 24.562314522194487,
        "220": 24.73075961006962,
        "230": 24.970598857299674,
        "240": 24.95375229611062,
        "250": 24.714397836125823,
        "260": 25.086064865085884,
        "270": 25.137724602302473,
        "280": 25.135807431472738,
        "290": 25.28347584458434,
        "300": 25.200952019783482
    },
    "result_time": {
        "10": {
            "forward": 1.4374381316484168,
            "backward": 2.972169702904859,
            "per_epoch_whole": 43270.3984375
        },
        "20": {
            "forward": 1.446786491000521,
            "backward": 2.9851763184250086,
            "per_epoch_whole": 43514.921875
        },
        "30": {
            "forward": 1.4493771629233971,
            "backward": 2.97814616852256,
            "per_epoch_whole": 43472.83984375
        },
        "40": {
            "forward": 1.444733235740123,
            "backward": 2.9752571694423837,
            "per_epoch_whole": 43366.8984375
        },
        "50": {
            "forward": 1.4413331665652929,
            "backward": 2.9732335643088676,
            "per_epoch_whole": 43345.23046875
        },
        "60": {
            "forward": 1.4478448265615689,
            "backward": 2.9802827511021417,
            "per_epoch_whole": 43476.46875
        },
        "70": {
            "forward": 1.4555311349823232,
            "backward": 2.98777801745851,
            "per_epoch_whole": 43585.296875
        },
        "80": {
            "forward": 1.4536156852997093,
            "backward": 2.983356160727235,
            "per_epoch_whole": 43515.66796875
        },
        "90": {
            "forward": 1.4356681077989242,
            "backward": 2.9689894155776404,
            "per_epoch_whole": 43196.40234375
        },
        "100": {
            "forward": 1.442692038097188,
            "backward": 2.97342206545459,
            "per_epoch_whole": 43373.67578125
        },
        "110": {
            "forward": 1.449587796457035,
            "backward": 2.9746155092640936,
            "per_epoch_whole": 43434.70703125
        },
        "120": {
            "forward": 1.4519456945888198,
            "backward": 2.9867809555109743,
            "per_epoch_whole": 43608.27734375
        },
        "130": {
            "forward": 1.4543270482826618,
            "backward": 2.9847767405392247,
            "per_epoch_whole": 43533.83984375
        },
        "140": {
            "forward": 1.4510789780674527,
            "backward": 2.976523604875622,
            "per_epoch_whole": 43443.53515625
        },
        "150": {
            "forward": 1.4489265674125835,
            "backward": 2.9746962199342004,
            "per_epoch_whole": 43395.5234375
        },
        "160": {
            "forward": 1.4526621520351697,
            "backward": 2.9891399492261574,
            "per_epoch_whole": 43573.8359375
        },
        "170": {
            "forward": 1.4391044850193715,
            "backward": 2.966037514609847,
            "per_epoch_whole": 43228.9140625
        },
        "180": {
            "forward": 1.4486971592408133,
            "backward": 2.9822463537195834,
            "per_epoch_whole": 43496.55078125
        },
        "190": {
            "forward": 1.4407627261968827,
            "backward": 2.9752316091170874,
            "per_epoch_whole": 43384.77734375
        },
        "200": {
            "forward": 1.446272917130517,
            "backward": 2.978463563642698,
            "per_epoch_whole": 43404.03125
        },
        "210": {
            "forward": 1.4559608545399192,
            "backward": 2.994188190499072,
            "per_epoch_whole": 43662.73828125
        },
        "220": {
            "forward": 1.4403974016786696,
            "backward": 2.987494252841254,
            "per_epoch_whole": 43513.03515625
        },
        "230": {
            "forward": 1.4479712873993789,
            "backward": 2.9822213706080207,
            "per_epoch_whole": 43485.28125
        },
        "240": {
            "forward": 1.4572372355185783,
            "backward": 2.9966757013285235,
            "per_epoch_whole": 43693.6875
        },
        "250": {
            "forward": 1.4435227682369294,
            "backward": 2.98891541766563,
            "per_epoch_whole": 43577.640625
        },
        "260": {
            "forward": 1.4457203252273227,
            "backward": 2.9790223820528214,
            "per_epoch_whole": 43408.578125
        },
        "270": {
            "forward": 1.4529727266128192,
            "backward": 2.987769855695498,
            "per_epoch_whole": 43568.109375
        },
        "280": {
            "forward": 1.4457482249575886,
            "backward": 2.9785039861747724,
            "per_epoch_whole": 43409.89453125
        },
        "290": {
            "forward": 1.450587585130165,
            "backward": 2.9879628714547826,
            "per_epoch_whole": 43553.171875
        },
        "300": {
            "forward": 1.4447674387518128,
            "backward": 2.98801503124225,
            "per_epoch_whole": 43559.0859375
        }
    }
}